xtsv_word/__init__.py
xtsv_word/word.py
xtsv_word-1.0.2.dist-info/WHEEL
xtsv_word-1.0.2.dist-info/METADATA
xtsv_word-1.0.2.dist-info/RECORD
