Metadata-Version: 2.1
Name: xtsv-word
Version: 1.0.2
Summary: A dataclass-like structure to make the handling of xtsv token attributes comfortable and transparent
Home-page: https://github.com/ril-lexknowrep/xtsv-word
License: LGPLv3
Author: Pethő Gergely
Author-email: pagstudium@gmail.com
Requires-Python: >=3.10,<4.0
Classifier: License :: Other/Proprietary License
Classifier: Programming Language :: Python :: 3
Classifier: Programming Language :: Python :: 3.10
